session_conductor_client/__init__.py
session_conductor_client/client.py
session_conductor_client-0.0.0.dist-info/LICENSE
session_conductor_client-0.0.0.dist-info/METADATA
session_conductor_client-0.0.0.dist-info/WHEEL
session_conductor_client-0.0.0.dist-info/top_level.txt
session_conductor_client-0.0.0.dist-info/RECORD
