Metadata-Version: 2.2
Name: session-conductor-client
Version: 0.0.0
Summary: Client library for interacting with the Session Conductor.
Home-page: https://github.com/chamindika33/session-conductor-client
Author: Chamindika Kodithuwakku
Author-email: chamindika1996@gmail.com
Classifier: Programming Language :: Python :: 3
Classifier: License :: OSI Approved :: MIT License
Classifier: Operating System :: OS Independent
Requires-Python: >=3.6
License-File: LICENSE
Requires-Dist: requests
Requires-Dist: schedule
Dynamic: author
Dynamic: author-email
Dynamic: classifier
Dynamic: description
Dynamic: description-content-type
Dynamic: home-page
Dynamic: requires-dist
Dynamic: requires-python
Dynamic: summary
